Workbook

Sheet Sales_Data
A1: TBL_SALES_RAW
A2: Customer_ID | B2: Order_ID | C2: Date | D2: Region | E2: Product | F2: Category | G2: Units | H2: Unit_Price ($) | I2: Discount | J2: Sales_Rep
A3: C001 | B3: 1001 | C3: 45658 | D3: North | E3: Quantum Headphones | F3: Electronics | G3: 2 | H3: 5000 | I3: 0.1 | J3: Raj
A4: C002 | B4: 1002 | C4: 45689 | D4: South | E4: AI Coffee Mug | F4: Home | G4: 5 | H4: 1200 | I4: 0.05 | J4: Priya
A5: C003 | B5: 1003 | C5: 45717 | D5: East | E5: Smart Lamp | F5: Home | G5: 3 | H5: 2500 | I5: 0.15 | J5: Amit
A6: C004 | B6: 1004 | C6: 45748 | D6: West | E6: Gaming Mouse | F6: Electronics | G6: 4 | H6: 1500 | I6: 0.2 | J6: Sneha
A7: C005 | B7: 1005 | C7: 45778 | D7: North | E7: Office Chair | F7: Furniture | G7: 1 | H7: 7000 | I7: 0.25 | J7: Raj
A8: C001 | B8: 1006 | C8: 45809 | D8: South | E8: Standing Desk | F8: Furniture | G8: 2 | H8: 15000 | I8: 0.1 | J8: Priya
A9: C006 | B9: 1007 | C9: 45839 | D9: East | E9: Quantum Headphones | F9: Electronics | G9: 1 | H9: 5000 | I9: 0.05 | J9: Amit
A10: C007 | B10: 1008 | C10: 45870 | D10: West | E10: AI Coffee Mug | F10: Home | G10: 6 | H10: 1200 | I10: 0.1 | J10: Sneha
A11: C008 | B11: 1009 | C11: 45901 | D11: North | E11: Gaming Mouse | F11: Electronics | G11: 3 | H11: 1500 | I11: 0 | J11: Raj
A12: C002 | B12: 1010 | C12: 45931 | D12: South | E12: Smart Lamp | F12: Home | G12: 2 | H12: 2500 | I12: 0.3 | J12: Priya
A13: C003 | B13: 1011 | C13: 45962 | D13: East | E13: Office Chair | F13: Furniture | G13: 1 | H13: 7000 | I13: 0.1 | J13: Amit
A14: C004 | B14: 1012 | C14: 45992 | D14: West | E14: Standing Desk | F14: Furniture | G14: 1 | H14: 15000 | I14: 0.15 | J14: Sneha
... A22: C004 | B22: 1020 | C22: 45677 | D22: West | E22: AI Coffee Mug | F22: Home | G22: 2 | H22: 1200 | I22: 0.25 | J22: Sneha

Sheet Customer_Data
A1: TBL_CUSTOMERS
A2: Customer_ID | B2: Customer_Name | C2: City | D2: Segment
A3: C001 | B3: Arjun Mehta | C3: Bangalore | D3: Retail
A4: C002 | B4: Neha Sharma | C4: Mumbai | D4: Corporate
A5: C003 | B5: Rohit Verma | C5: Delhi | D5: Retail
A6: C004 | B6: Pooja Iyer | C6: Chennai | D6: Corporate
A7: C005 | B7: Karan Patel | C7: Ahmedabad | D7: Retail
A8: C006 | B8: Simran Kaur | C8: Punjab | D8: Corporate
A9: C007 | B9: Vikram Singh | C9: Jaipur | D9: Retail
A10: C008 | B10: Ananya Das | C10: Kolkata | D10: Corporate

Sheet Product_Data
A1: TBL_PRODUCTS
A2: Product | B2: Category | C2: Cost_Price ($)
A3: Quantum Headphones | B3: Electronics | C3: 3000
A4: AI Coffee Mug | B4: Home | C4: 700
A5: Smart Lamp | B5: Home | C5: 1500
A6: Gaming Mouse | B6: Electronics | C6: 800
A7: Office Chair | B7: Furniture | C7: 4000
A8: Standing Desk | B8: Furniture | C8: 10000

Sheet Targets
A1: TBL_TARGETS | D1: REGION & REP DATA | G1: UNIQUE SALES REP
A2: Sales_Rep | B2: Monthly_Target ($) | D2: Region | E2: Sales_Rep | G2: {=_xlfn.UNIQUE(D2:E22)} -> Region | H2: Sales_Rep
A3: Raj | B3: 50000 | D3: North | E3: Raj | G3: North | H3: Raj
A4: Priya | B4: 60000 | D4: South | E4: Priya | G4: South | H4: Priya
A5: Amit | B5: 55000 | D5: East | E5: Amit | G5: East | H5: Amit
A6: Sneha | B6: 52000 | D6: West | E6: Sneha | G6: West | H6: Sneha
D7: North | E7: Raj
D8: South | E8: Priya
D9: East | E9: Amit
D10: West | E10: Sneha
D11: North | E11: Raj
D12: South | E12: Priya
D13: East | E13: Amit
D14: West | E14: Sneha
D15: North | E15: Raj
D16: South | E16: Priya
D17: East | E17: Amit
D18: West | E18: Sneha
... D22: West | E22: Sneha

Sheet Model
A1: Customer Name | B1: City | C1: Segment | D1: {=tbl_sales_raw[#All]} -> Customer_ID | E1: Order_ID | F1: Date | G1: Region | H1: Product | I1: Category | J1: Units | K1: Unit_Price ($) | L1: Discount | M1: Sales_Rep | N1: Cost Price ($) | O1: Revenue ($) | P1: Discount Amount ($) | Q1: Net Revenue ($) | R1: Profit ($) | S1: Profit Performance | T1: High Value | U1: High Risk | V1: Order Value | W1: Category Confirmation
A2: {=_xlfn.XLOOKUP(D2:D21,tbl_customers[Customer_ID],tbl_customers[Customer_Name],"N/A",0,1)} -> Arjun Mehta | B2: {=_xlfn.XLOOKUP(D2:D21,tbl_customers[Customer_ID],tbl_customers[City],"N/A",0,1)} -> Bangalore | C2: {=_xlfn.XLOOKUP(D2:D21,tbl_customers[Customer_ID],tbl_customers[Segment],"N/A",0,1)} -> Retail | D2: C001 | E2: 1001 | F2: 45658 | G2: North | H2: Quantum Headphones | I2: Electronics | J2: 2 | K2: 5000 | L2: 0.1 | M2: Raj | N2: {=_xlfn.XLOOKUP(H2:H21,tbl_products[Product],tbl_products[Cost_Price ($)],"N/A",0,1)} -> 3000 | O2: {=K2:K21*J2:J21} -> 10000 | P2: {=O2:O21*L2:L21} -> 1000 | Q2: {=O2:O21-P2:P21} -> 9000 | R2: {=Q2:Q21-(_xlfn.ANCHORARRAY(N2)*J2:J21)} -> 3000 | S2: {=_xlfn.IFS(_xlfn.ANCHORARRAY(R2)>5000,"Excellent",(_xlfn.ANCHORARRAY(R2)>=2000)*(_xlfn.ANCHORARRAY(R2)<=5000),"Good",_xlfn.ANCHORARRAY(R2)<2000,"Poor")} -> Good | T2: {=IF((_xlfn.ANCHORARRAY(Q2)>10000)*((I2:I21="Electronics")+(I2:I21="Furniture")),TRUE,FALSE)} -> FALSE | U2: {=IF((_xlfn.ANCHORARRAY(R2)<2000)+(L2:L21>25%),TRUE,FALSE)} -> FALSE | V2: {=_xlfn.IFS(_xlfn.ANCHORARRAY(T2)=TRUE,"High Value",_xlfn.ANCHORARRAY(U2)=TRUE,"High Risk",(_xlfn.ANCHORARRAY(T2)=FALSE)+(_xlfn.ANCHORARRAY(U2)=FALSE),"Normal")} -> Normal | W2: {=_xlfn.XLOOKUP(H2:H21,tbl_products[Product],tbl_products[Category],"N/A",0,1)=I2:I21} -> TRUE
A3: Neha Sharma | B3: Mumbai | C3: Corporate | D3: C002 | E3: 1002 | F3: 45689 | G3: South | H3: AI Coffee Mug | I3: Home | J3: 5 | K3: 1200 | L3: 0.05 | M3: Priya | N3: 700 | O3: 6000 | P3: 300 | Q3: 5700 | R3: 2200 | S3: Good | T3: FALSE | U3: FALSE | V3: Normal | W3: TRUE
A4: Rohit Verma | B4: Delhi | C4: Retail | D4: C003 | E4: 1003 | F4: 45717 | G4: East | H4: Smart Lamp | I4: Home | J4: 3 | K4: 2500 | L4: 0.15 | M4: Amit | N4: 1500 | O4: 7500 | P4: 1125 | Q4: 6375 | R4: 1875 | S4: Poor | T4: FALSE | U4: TRUE | V4: High Risk | W4: TRUE
A5: Pooja Iyer | B5: Chennai | C5: Corporate | D5: C004 | E5: 1004 | F5: 45748 | G5: West | H5: Gaming Mouse | I5: Electronics | J5: 4 | K5: 1500 | L5: 0.2 | M5: Sneha | N5: 800 | O5: 6000 | P5: 1200 | Q5: 4800 | R5: 1600 | S5: Poor | T5: FALSE | U5: TRUE | V5: High Risk | W5: TRUE
A6: Karan Patel | B6: Ahmedabad | C6: Retail | D6: C005 | E6: 1005 | F6: 45778 | G6: North | H6: Office Chair | I6: Furniture | J6: 1 | K6: 7000 | L6: 0.25 | M6: Raj | N6: 4000 | O6: 7000 | P6: 1750 | Q6: 5250 | R6: 1250 | S6: Poor | T6: FALSE | U6: TRUE | V6: High Risk | W6: TRUE
A7: Arjun Mehta | B7: Bangalore | C7: Retail | D7: C001 | E7: 1006 | F7: 45809 | G7: South | H7: Standing Desk | I7: Furniture | J7: 2 | K7: 15000 | L7: 0.1 | M7: Priya | N7: 10000 | O7: 30000 | P7: 3000 | Q7: 27000 | R7: 7000 | S7: Excellent | T7: TRUE | U7: FALSE | V7: High Value | W7: TRUE
A8: Simran Kaur | B8: Punjab | C8: Corporate | D8: C006 | E8: 1007 | F8: 45839 | G8: East | H8: Quantum Headphones | I8: Electronics | J8: 1 | K8: 5000 | L8: 0.05 | M8: Amit | N8: 3000 | O8: 5000 | P8: 250 | Q8: 4750 | R8: 1750 | S8: Poor | T8: FALSE | U8: TRUE | V8: High Risk | W8: TRUE
A9: Vikram Singh | B9: Jaipur | C9: Retail | D9: C007 | E9: 1008 | F9: 45870 | G9: West | H9: AI Coffee Mug | I9: Home | J9: 6 | K9: 1200 | L9: 0.1 | M9: Sneha | N9: 700 | O9: 7200 | P9: 720 | Q9: 6480 | R9: 2280 | S9: Good | T9: FALSE | U9: FALSE | V9: Normal | W9: TRUE
A10: Ananya Das | B10: Kolkata | C10: Corporate | D10: C008 | E10: 1009 | F10: 45901 | G10: North | H10: Gaming Mouse | I10: Electronics | J10: 3 | K10: 1500 | L10: 0 | M10: Raj | N10: 800 | O10: 4500 | P10: 0 | Q10: 4500 | R10: 2100 | S10: Good | T10: FALSE | U10: FALSE | V10: Normal | W10: TRUE
A11: Neha Sharma | B11: Mumbai | C11: Corporate | D11: C002 | E11: 1010 | F11: 45931 | G11: South | H11: Smart Lamp | I11: Home | J11: 2 | K11: 2500 | L11: 0.3 | M11: Priya | N11: 1500 | O11: 5000 | P11: 1500 | Q11: 3500 | R11: 500 | S11: Poor | T11: FALSE | U11: TRUE | V11: High Risk | W11: TRUE
A12: Rohit Verma | B12: Delhi | C12: Retail | D12: C003 | E12: 1011 | F12: 45962 | G12: East | H12: Office Chair | I12: Furniture | J12: 1 | K12: 7000 | L12: 0.1 | M12: Amit | N12: 4000 | O12: 7000 | P12: 700 | Q12: 6300 | R12: 2300 | S12: Good | T12: FALSE | U12: FALSE | V12: Normal | W12: TRUE
A13: Pooja Iyer | B13: Chennai | C13: Corporate | D13: C004 | E13: 1012 | F13: 45992 | G13: West | H13: Standing Desk | I13: Furniture | J13: 1 | K13: 15000 | L13: 0.15 | M13: Sneha | N13: 10000 | O13: 15000 | P13: 2250 | Q13: 12750 | R13: 2750 | S13: Good | T13: TRUE | U13: FALSE | V13: High Value | W13: TRUE
A14: Karan Patel | B14: Ahmedabad | C14: Retail | D14: C005 | E14: 1013 | F14: 45670 | G14: North | H14: Quantum Headphones | I14: Electronics | J14: 2 | K14: 5000 | L14: 0.2 | M14: Raj | N14: 3000 | O14: 10000 | P14: 2000 | Q14: 8000 | R14: 2000 | S14: Good | T14: FALSE | U14: FALSE | V14: Normal | W14: TRUE
... A21: Pooja Iyer | B21: Chennai | C21: Corporate | D21: C004 | E21: 1020 | F21: 45677 | G21: West | H21: AI Coffee Mug | I21: Home | J21: 2 | K21: 1200 | L21: 0.25 | M21: Sneha | N21: 700 | O21: 2400 | P21: 600 | Q21: 1800 | R21: 400 | S21: Poor | T21: FALSE | U21: TRUE | V21: High Risk | W21: TRUE

Sheet Analysis
B3: Total Revenue ($) | C3: =SUM(_xlfn.ANCHORARRAY(Model!O2)) -> 191900 | F3: Total Net Sales | I3: ="Total Net Sales "&J4 &" or " &K4 -> Total Net Sales North or South | M3: Sales Performance
B4: Total Net Sales ($) | C4: =SUM(_xlfn.ANCHORARRAY(Model!Q2)) -> 166665 | F4: Region | G4: North | I4: Regions | J4: North | K4: South | M4: Sales Rep | N4: Monthly Target ($) | O4: Actual Sales ($) | P4: Status
B5: Total Profits ($) | C5: =SUM(_xlfn.ANCHORARRAY(Model!R2)) -> 48665 | F5: Catrgory | G5: Electronics | I5: Total Sales ($) | J5: {=SUM(IF((Model!G2:G21=Analysis!J4:K4),_xlfn.ANCHORARRAY(Model!Q2),))} -> 98160 | M5: {=_xlfn._xlws.SORT(tbl_targets[],1,1,FALSE)} -> Amit | N5: 55000 | O5: {=SUMIFS(_xlfn.ANCHORARRAY(Model!Q2),Model!M2:M21,Analysis!M5:M8)} -> 37675 | P5: {=IF(_xlfn.ANCHORARRAY(O5)>=N5:N8,"Achieved","Not Met")} -> Not Met
B6: Total Orders ($) | C6: =SUM(Model!J2:J21) -> 52 | F6: Total ($) | G6: =SUMIFS(_xlfn.ANCHORARRAY(Model!Q2),Model!G2:G21,Analysis!G4,Model!I2:I21,Analysis!G5) -> 21500 | M6: Priya | N6: 60000 | O6: 64760 | P6: Achieved
B7: Average Discount % | C7: =AVERAGE(Model!L2:L21) -> 0.125 | I7: ="Total Orders by "&J8 &" or "&K8 -> Total Orders by Raj or Amit | M7: Raj | N7: 50000 | O7: 33400 | P7: Not Met
F8: Total No. of Orders | I8: Sales Rep | J8: Raj | K8: Amit | M8: Sneha | N8: 52000 | O8: 30830 | P8: Not Met
F9: Segment | G9: Corporate | I9: Total Orders | J9: {=SUM(IF(Model!M2:M21=Analysis!J8:K8,Model!J2:J21,))} -> 22
B10: BUSINESS PERFORMANCE INSIGHTS | F10: Discount | G10: >10% | M10: All Unique
B11: Best performing region (By Profit) | C11: =INDEX(B19:B22,MATCH(MAX(_xlfn.ANCHORARRAY(D19)),_xlfn.ANCHORARRAY(D19),0)) -> South | F11: Total No. | G11: =COUNTIFS(_xlfn.ANCHORARRAY(Model!C2),Analysis!G9,Model!L2:L21,Analysis!G10) -> 5 | I11: ="Region:"&J12 &" & Category:" &J13 &" | discount: "&J14 -> Region:East & Category:Electronics | discount: >20% | M11: Regions | N11: {=TRANSPOSE(_xlfn.UNIQUE(_xlfn._xlws.SORT(Model!G2:G21,,1,FALSE),FALSE,FALSE))} -> East | O11: North | P11: South | Q11: West
B12: Most Profitable Product | C12: =INDEX(_xlfn.ANCHORARRAY(B26),MATCH(MAX(_xlfn.ANCHORARRAY(C26)),_xlfn.ANCHORARRAY(C26),0)) -> Standing Desk | I12: Region | J12: East | M12: Salea Reps | N12: {=TRANSPOSE(_xlfn.UNIQUE(_xlfn._xlws.SORT(Model!M2:M21,,1,FALSE),FALSE,FALSE))} -> Amit | O12: Priya | P12: Raj | Q12: Sneha
B13: Best Sales Rep | C13: =INDEX(M5:M8,MATCH(MAX(N5:N8),N5:N8,0)) -> Priya | F13: Average Profit | I13: Category | J13: Electronics | M13: Products | N13: {=TRANSPOSE(_xlfn.UNIQUE(_xlfn._xlws.SORT(Model!H2:H21),FALSE,FALSE))} -> AI Coffee Mug | O13: Gaming Mouse | P13: Office Chair | Q13: Quantum Headphones | R13: Smart Lamp | S13: Standing Desk
B14: Worst Sales Rep | C14: =INDEX(M6:M9,MATCH(MIN(N6:N9),N6:N9,0)) -> Raj | F14: Region | G14: South | I14: Discount % | J14: >20%
B15: Does Discount improve profit or reduce it | C15: Reduce | F15: Avg Profit ($) | G15: =AVERAGEIFS(_xlfn.ANCHORARRAY(Model!R2),Model!G2:G21,Analysis!G14) -> 3092 | I15: Total Profit ($) | J15: =SUMIFS(_xlfn.ANCHORARRAY(Model!R2),Model!G2:G21,Analysis!J12,Model!I2:I21,Analysis!J13) + SUMIFS(_xlfn.ANCHORARRAY(Model!R2),Model!L2:L21,Analysis!J14) - SUMIFS(_xlfn.ANCHORARRAY(Model!R2),Model!G2:G21,Analysis!J12,Model!I2:I21,Analysis!J13,Model!L2:L21,Analysis!J14) -> 11150 | M15: Profits from Largest to Smallest ($)
M16: {=_xlfn.SEQUENCE(35-15,,1,1)} -> 1 | N16: {=_xlfn._xlws.SORT(_xlfn.ANCHORARRAY(Model!R2),,-1,FALSE)} -> 7000
B17: Profits By Region | F17: ="Total Profit by Sales Rep "&G18 -> Total Profit by Sales Rep Raj | I17: Profit by Segment | M17: 2 | N17: 4500
B18: Region | C18: Net Revenue ($) | D18: Profit ($) | F18: Sales Rep | G18: Raj | I18: Segment | J18: Net Revenue ($) | K18: Profit ($) | M18: 3 | N18: 4000
B19: North | C19: {=SUMIFS(_xlfn.ANCHORARRAY(Model!Q2),Model!G2:G21,Analysis!B19:B22)} -> 33400 | D19: {=SUMIFS(_xlfn.ANCHORARRAY(Model!R2),Model!G2:G21,B19:B22)} -> 11000 | F19: Total Profit ($) | G19: =SUMIFS(_xlfn.ANCHORARRAY(Model!R2),Model!M2:M21,Analysis!G18) -> 11000 | I19: {=_xlfn.UNIQUE(_xlfn._xlws.SORT(_xlfn.ANCHORARRAY(Model!C2)))} -> Corporate | J19: {=SUMIFS(_xlfn.ANCHORARRAY(Model!Q2),_xlfn.ANCHORARRAY(Model!C2),_xlfn.ANCHORARRAY(Analysis!I19))} -> 71360 | K19: {=SUMIFS(_xlfn.ANCHORARRAY(Model!R2),_xlfn.ANCHORARRAY(Model!C2),_xlfn.ANCHORARRAY(Analysis!I19))} -> 19060 | M19: 4 | N19: 3000
B20: South | C20: 64760 | D20: 15460 | I20: Retail | J20: 95305 | K20: 29605 | M20: 5 | N20: 2750
B21: East | C21: 37675 | D21: 13175 | F21: Profit with discount Vs Without | M21: 6 | N21: 2750
B22: West | C22: 30830 | D22: 9030 | F22: Profit without Discount ($) | G22: {=SUM(_xlfn.ANCHORARRAY(Model!O2))- SUM(_xlfn.ANCHORARRAY(Model!N2)*Model!J2:J21)} -> 73900 | M22: 7 | N22: 2650
F23: Profit with Discount ($) | G23: =SUM(_xlfn.ANCHORARRAY(Model!R2)) -> 48665 | M23: 8 | N23: 2300
B24: Most Profitable Product | M24: 9 | N24: 2280
B25: Product Name | C25: Profit | F25: High Discount but Profitable Orders | M25: 10 | N25: 2200
B26: {=_xlfn.UNIQUE(_xlfn._xlws.SORT(Model!H2:H21,,1,FALSE),FALSE,FALSE)} -> AI Coffee Mug | C26: {=SUMIFS(_xlfn.ANCHORARRAY(Model!R2),Model!H2:H21,_xlfn.ANCHORARRAY(Analysis!B26))} -> 6640 | F26: Discount % above | G26: 0.2 | M26: 11 | N26: 2100
B27: Gaming Mouse | C27: 6450 | F27: Profit above | G27: 3000 | M27: 12 | N27: 2000
B28: Office Chair | C28: 6200 | F28: Products | G28: {=_xlfn._xlws.FILTER(_xlfn.CHOOSECOLS(Model!H2:R21,2,1,4,9,10),((Model!L2:L21>G26)*(_xlfn.ANCHORARRAY(Model!R2)>Analysis!G27)>=1),"None Available")} -> None Available | M28: 13 | N28: 2000
B29: Quantum Headphones | C29: 11250 | M29: 14 | N29: 1875
B30: Smart Lamp | C30: 4375 | M30: 15 | N30: 1760
B31: Standing Desk | C31: 13750 | M31: 16 | N31: 1750
M32: 17 | N32: 1600
M33: 18 | N33: 1250
M34: 19 | N34: 500
M35: 20 | N35: 400

Sheet Dashboard
B2: Total Sales ($) | C2: =Analysis!C4 -> 166665
B3: Total Profit ($) | C3: =Analysis!C5 -> 48665
B4: Avg. Discount % | C4: =Analysis!C7 -> 0.125
B5: Target Achievement % | C5: =(SUM(_xlfn.ANCHORARRAY(Analysis!O5))/SUM(Analysis!N5:N8)) -> 0.76804147

Sheet Insights
A1: INSIGHTS
A2: 1 | B2: Which Region Is the strongest and why ?
A3: Ans | B3: The Southern Region is by far the region with the maximum net revenue and profits.
A4: 2 | B4: Which product drives profit?
A5: Ans | B5: The Standing desk drives the most profits.
A6: 3 | B6: Are discounts effective ?
A7: Ans | B7: Too little data to judge accurately.
A8: 4 | B8: Who is the top and bottom sales rep?
A9: Ans | B9: Priya and Raj respectively.
A10: 5 | B10: Are corporate customers more profitable ?
A11: Ans | B11: No, retail customers drive more revenues and profits.
